prylint/__init__.py
prylint/cli.py
prylint/linter.py
prylint/bin/prylint
prylint-0.1.1.dist-info/licenses/LICENSE
prylint-0.1.1.dist-info/METADATA
prylint-0.1.1.dist-info/WHEEL
prylint-0.1.1.dist-info/entry_points.txt
prylint-0.1.1.dist-info/top_level.txt
prylint-0.1.1.dist-info/RECORD
