Metadata-Version: 2.4
Name: prylint
Version: 0.1.1
Summary: A fast Python linter written in Rust. Faster than pylint, slower than ruff. Catches more issues than ruff, less than pylint
Home-page: https://github.com/adamraudonis/prylint
Author: Adam Raudonis
Author-email: Adam Raudonis <adam.raudonis@gmail.com>
License: MIT
Project-URL: Homepage, https://github.com/adamraudonis/prylint
Project-URL: Issues, https://github.com/adamraudonis/prylint/issues
Project-URL: Repository, https://github.com/adamraudonis/prylint
Keywords: linter,static-analysis,python,rust,fast
Classifier: Development Status :: 3 - Alpha
Classifier: Intended Audience :: Developers
Classifier: License :: OSI Approved :: MIT License
Classifier: Programming Language :: Python :: 3
Classifier: Programming Language :: Python :: 3.8
Classifier: Programming Language :: Python :: 3.9
Classifier: Programming Language :: Python :: 3.10
Classifier: Programming Language :: Python :: 3.11
Classifier: Programming Language :: Python :: 3.12
Classifier: Programming Language :: Rust
Classifier: Topic :: Software Development :: Quality Assurance
Classifier: Topic :: Software Development :: Testing
Classifier: Operating System :: OS Independent
Requires-Python: >=3.8
License-File: LICENSE
Provides-Extra: dev
Requires-Dist: pytest>=7.0; extra == "dev"
Requires-Dist: pylint>=2.0; extra == "dev"
Dynamic: author
Dynamic: home-page
Dynamic: license-file
Dynamic: requires-python
